README.txt
setup.py
Bananas.egg-info/PKG-INFO
Bananas.egg-info/SOURCES.txt
Bananas.egg-info/dependency_links.txt
Bananas.egg-info/requires.txt
Bananas.egg-info/top_level.txt
banana/__init__.py
banana/utils.py
bin/this-is-bananas.py