Metadata-Version: 1.0
Name: Bananas
Version: 0.1.2
Summary: My Bananas project. Learning how to use project skeletons and make packages.
Home-page: http://pypi.python.org/pypi/Bananas/
Author: Huyen Tran
Author-email: hey.huyen@gmail.com
License: UNKNOWN
Download-URL: http://pypi.python.org/pypi/Bananas/
Platform: UNKNOWN
